Metadata-Version: 2.4
Name: docs-cli
Version: 0.1.1
Summary: Um toolkit para processamento e avaliação de documentação.
Author-email: Paulo Guilherme Pilott <seuemail@example.com>
License-Expression: MIT
Classifier: Programming Language :: Python :: 3
Classifier: Operating System :: OS Independent
Classifier: Development Status :: 3 - Alpha
Classifier: Intended Audience :: Developers
Classifier: Topic :: Documentation
Classifier: Topic :: Utilities
Classifier: Environment :: Console
Requires-Python: >=3.8
Requires-Dist: google-generativeai
Requires-Dist: python-dotenv
Requires-Dist: numpy
Requires-Dist: pandas
